SquirrelDB-0.2.5.dist-info/METADATA
SquirrelDB-0.2.5.dist-info/RECORD
SquirrelDB-0.2.5.dist-info/WHEEL
SquirrelDB-0.2.5.dist-info/top_level.txt
squirreldb/__init__.py
squirreldb/commands/__init__.py
squirreldb/commands/listOperations.py
squirreldb/commands/listOperationsImpl.py
squirreldb/commands/stringOperations.py
squirreldb/commands/stringOperationsImpl.py
squirreldb/engine/__init__.py
squirreldb/engine/main.py
squirreldb/engine/operations.py
squirreldb/persistence/__init__.py
squirreldb/persistence/jsonPersistence.py
squirreldb/persistence/persistence.py
squirreldb/persistence/storageState.py
